hardware/hard3/mul.v
module mul(A, B, O, ck, start, fin);
input[7:0] A, B;
input ck, start;
output [16:0] O;
output fin;
reg [7:0] INA, INB;
reg [16:0] O;
reg [3:0] st;
reg fin;
always @(posedge ck) begin
    if( start == 1) begin
    O <= 0;
    st <= 0;
    fin <= 0;
    INA <= A; INB <= B;
end else begin
    O<=(O<<1) + INA * INB[7-st];
    st <= st +1;
    if(st == 7) begin
    fin <= 1;
    end
    else if(st == 8) begin
    fin <= 0;
end

end
end
endmodule

hardware/hard3/multest2.v
module  multest;
reg	[7:0]	A, B;
reg	ck;
reg	start;
reg	[3:0] st;
wire	[16:0] O;
reg	[16:0] OR;
initial begin
	ck=0;
	start=0;
	st=0;
	$dumpvars;
	$dumpfile("mul.vcd");
	$monitor( "%t\tA=%h, B=%h, (OUT=%h) OUT=%h", $time, A, B, O, OR );
	A=0;
	B=0;
end
mul	MUL(A , B , O ,  ck, start,fin);
always	#10	ck = ~ck;
always @(negedge ck) begin
	if( st == 0 ) begin
	    start <= 1;
	end
	else start <= 0;
	if( fin == 1 ) begin
	    OR <= O;
	    {B,A} <= {B,A} + 1;
	   st <= 0;
            if( O != A*B ) begin
                  $finish;
            end
            if( A == 'h f && B == 'h f ) begin
               $display( "OK\n" );
               $finish;
            end
	end else  st <= st+1;
end
endmodule

hardware/hard3/dump.vcd
$date
	Fri Apr 26 11:41:32 2019
$end
$version
	Icarus Verilog
$end
$timescale
	1s
$end
$scope module multest $end
$var wire 1 ! fin $end
$var wire 17 " O [16:0] $end
$var reg 8 # A [7:0] $end
$var reg 8 $ B [7:0] $end
$var reg 17 % OR [16:0] $end
$var reg 1 & ck $end
$var reg 4 ' st [3:0] $end
$var reg 1 ( start $end
$scope module MUL $end
$var wire 8 ) A [7:0] $end
$var wire 8 * B [7:0] $end
$var wire 1 & ck $end
$var wire 1 ( start $end
$var reg 8 + INA [7:0] $end
$var reg 8 , INB [7:0] $end
$var reg 17 - O [16:0] $end
$var reg 1 ! fin $end
$var reg 4 . st [3:0] $end
$upscope $end
$upscope $end
$enddefinitions $end
#0
$dumpvars
bx .
bx -
bx ,
bx +
b0 *
b0 )
0(
b0 '
0&
bx %
b0 $
b0 #
bx "
x!
$end
#10
1&
#20
b1 '
1(
0&
#30
b0 ,
b0 +
0!
b0 .
b0 "
b0 -
1&
#40
b10 '
0(
0&
#50
b1 .
1&
#60
b11 '
0&
#70
b10 .
1&
#80
b100 '
0&
#90
b11 .
1&
#100
b101 '
0&
#110
b100 .
1&
#120
b110 '
0&
#130
b101 .
1&
#140
b111 '
0&
#150
b110 .
1&
#160
b1000 '
0&
#170
b111 .
1&
#180
b1001 '
0&
#190
1!
b1000 .
1&
#200
b0 '
b1 #
b1 )
b0 %
0&
#210
0!
b1001 .
bx "
bx -
1&
#220
b1 '
1(
0&
#230
b1 +
b0 .
b0 "
b0 -
1&
#240
b10 '
0(
0&
#250
b1 .
1&
#260
b11 '
0&
#270
b10 .
1&
#280
b100 '
0&
#290
b11 .
1&
#300
b101 '
0&
#310
b100 .
1&
#320
b110 '
0&
#330
b101 .
1&
#340
b111 '
0&
#350
b110 .
1&
#360
b1000 '
0&
#370
b111 .
1&
#380
b1001 '
0&
#390
1!
b1000 .
1&
#400
b0 '
b10 #
b10 )
0&
#410
0!
b1001 .
bx "
bx -
1&
#420
b1 '
1(
0&
#430
b10 +
b0 .
b0 "
b0 -
1&
#440
b10 '
0(
0&
#450
b1 .
1&
#460
b11 '
0&
#470
b10 .
1&
#480
b100 '
0&
#490
b11 .
1&
#500
b101 '
0&
#510
b100 .
1&
#520
b110 '
0&
#530
b101 .
1&
#540
b111 '
0&
#550
b110 .
1&
#560
b1000 '
0&
#570
b111 .
1&
#580
b1001 '
0&
#590
1!
b1000 .
1&
#600
b0 '
b11 #
b11 )
0&
#610
0!
b1001 .
bx "
bx -
1&
#620
b1 '
1(
0&
#630
b11 +
b0 .
b0 "
b0 -
1&
#640
b10 '
0(
0&
#650
b1 .
1&
#660
b11 '
0&
#670
b10 .
1&
#680
b100 '
0&
#690
b11 .
1&
#700
b101 '
0&
#710
b100 .
1&
#720
b110 '
0&
#730
b101 .
1&
#740
b111 '
0&
#750
b110 .
1&
#760
b1000 '
0&
#770
b111 .
1&
#780
b1001 '
0&
#790
1!
b1000 .
1&
#800
b0 '
b100 #
b100 )
0&
#810
0!
b1001 .
bx "
bx -
1&
#820
b1 '
1(
0&
#830
b100 +
b0 .
b0 "
b0 -
1&
#840
b10 '
0(
0&
#850
b1 .
1&
#860
b11 '
0&
#870
b10 .
1&
#880
b100 '
0&
#890
b11 .
1&
#900
b101 '
0&
#910
b100 .
1&
#920
b110 '
0&
#930
b101 .
1&
#940
b111 '
0&
#950
b110 .
1&
#960
b1000 '
0&
#970
b111 .
1&
#980
b1001 '
0&
#990
1!
b1000 .
1&
#1000
b0 '
b101 #
b101 )
0&
#1010
0!
b1001 .
bx "
bx -
1&
#1020
b1 '
1(
0&
#1030
b101 +
b0 .
b0 "
b0 -
1&
#1040
b10 '
0(
0&
#1050
b1 .
1&
#1060
b11 '
0&
#1070
b10 .
1&
#1080
b100 '
0&
#1090
b11 .
1&
#1100
b101 '
0&
#1110
b100 .
1&
#1120
b110 '
0&
#1130
b101 .
1&
#1140
b111 '
0&
#1150
b110 .
1&
#1160
b1000 '
0&
#1170
b111 .
1&
#1180
b1001 '
0&
#1190
1!
b1000 .
1&
#1200
b0 '
b110 #
b110 )
0&
#1210
0!
b1001 .
bx "
bx -
1&
#1220
b1 '
1(
0&
#1230
b110 +
b0 .
b0 "
b0 -
1&
#1240
b10 '
0(
0&
#1250
b1 .
1&
#1260
b11 '
0&
#1270
b10 .
1&
#1280
b100 '
0&
#1290
b11 .
1&
#1300
b101 '
0&
#1310
b100 .
1&
#1320
b110 '
0&
#1330
b101 .
1&
#1340
b111 '
0&
#1350
b110 .
1&
#1360
b1000 '
0&
#1370
b111 .
1&
#1380
b1001 '
0&
#1390
1!
b1000 .
1&
#1400
b0 '
b111 #
b111 )
0&
#1410
0!
b1001 .
bx "
bx -
1&
#1420
b1 '
1(
0&
#1430
b111 +
b0 .
b0 "
b0 -
1&
#1440
b10 '
0(
0&
#1450
b1 .
1&
#1460
b11 '
0&
#1470
b10 .
1&
#1480
b100 '
0&
#1490
b11 .
1&
#1500
b101 '
0&
#1510
b100 .
1&
#1520
b110 '
0&
#1530
b101 .
1&
#1540
b111 '
0&
#1550
b110 .
1&
#1560
b1000 '
0&
#1570
b111 .
1&
#1580
b1001 '
0&
#1590
1!
b1000 .
1&
#1600
b0 '
b1000 #
b1000 )
0&
#1610
0!
b1001 .
bx "
bx -
1&
#1620
b1 '
1(
0&
#1630
b1000 +
b0 .
b0 "
b0 -
1&
#1640
b10 '
0(
0&
#1650
b1 .
1&
#1660
b11 '
0&
#1670
b10 .
1&
#1680
b100 '
0&
#1690
b11 .
1&
#1700
b101 '
0&
#1710
b100 .
1&
#1720
b110 '
0&
#1730
b101 .
1&
#1740
b111 '
0&
#1750
b110 .
1&
#1760
b1000 '
0&
#1770
b111 .
1&
#1780
b1001 '
0&
#1790
1!
b1000 .
1&
#1800
b0 '
b1001 #
b1001 )
0&
#1810
0!
b1001 .
bx "
bx -
1&
#1820
b1 '
1(
0&
#1830
b1001 +
b0 .
b0 "
b0 -
1&
#1840
b10 '
0(
0&
#1850
b1 .
1&
#1860
b11 '
0&
#1870
b10 .
1&
#1880
b100 '
0&
#1890
b11 .
1&
#1900
b101 '
0&
#1910
b100 .
1&
#1920
b110 '
0&
#1930
b101 .
1&
#1940
b111 '
0&
#1950
b110 .
1&
#1960
b1000 '
0&
#1970
b111 .
1&
#1980
b1001 '
0&
#1990
1!
b1000 .
1&
#2000
b0 '
b1010 #
b1010 )
0&
#2010
0!
b1001 .
bx "
bx -
1&
#2020
b1 '
1(
0&
#2030
b1010 +
b0 .
b0 "
b0 -
1&
#2040
b10 '
0(
0&
#2050
b1 .
1&
#2060
b11 '
0&
#2070
b10 .
1&
#2080
b100 '
0&
#2090
b11 .
1&
#2100
b101 '
0&
#2110
b100 .
1&
#2120
b110 '
0&
#2130
b101 .
1&
#2140
b111 '
0&
#2150
b110 .
1&
#2160
b1000 '
0&
#2170
b111 .
1&
#2180
b1001 '
0&
#2190
1!
b1000 .
1&
#2200
b0 '
b1011 #
b1011 )
0&
#2210
0!
b1001 .
bx "
bx -
1&
#2220
b1 '
1(
0&
#2230
b1011 +
b0 .
b0 "
b0 -
1&
#2240
b10 '
0(
0&
#2250
b1 .
1&
#2260
b11 '
0&
#2270
b10 .
1&
#2280
b100 '
0&
#2290
b11 .
1&
#2300
b101 '
0&
#2310
b100 .
1&
#2320
b110 '
0&
#2330
b101 .
1&
#2340
b111 '
0&
#2350
b110 .
1&
#2360
b1000 '
0&
#2370
b111 .
1&
#2380
b1001 '
0&
#2390
1!
b1000 .
1&
#2400
b0 '
b1100 #
b1100 )
0&
#2410
0!
b1001 .
bx "
bx -
1&
#2420
b1 '
1(
0&
#2430
b1100 +
b0 .
b0 "
b0 -
1&
#2440
b10 '
0(
0&
#2450
b1 .
1&
#2460
b11 '
0&
#2470
b10 .
1&
#2480
b100 '
0&
#2490
b11 .
1&
#2500
b101 '
0&
#2510
b100 .
1&
#2520
b110 '
0&
#2530
b101 .
1&
#2540
b111 '
0&
#2550
b110 .
1&
#2560
b1000 '
0&
#2570
b111 .
1&
#2580
b1001 '
0&
#2590
1!
b1000 .
1&
#2600
b0 '
b1101 #
b1101 )
0&
#2610
0!
b1001 .
bx "
bx -
1&
#2620
b1 '
1(
0&
#2630
b1101 +
b0 .
b0 "
b0 -
1&
#2640
b10 '
0(
0&
#2650
b1 .
1&
#2660
b11 '
0&
#2670
b10 .
1&
#2680
b100 '
0&
#2690
b11 .
1&
#2700
b101 '
0&
#2710
b100 .
1&
#2720
b110 '
0&
#2730
b101 .
1&
#2740
b111 '
0&
#2750
b110 .
1&
#2760
b1000 '
0&
#2770
b111 .
1&
#2780
b1001 '
0&
#2790
1!
b1000 .
1&
#2800
b0 '
b1110 #
b1110 )
0&
#2810
0!
b1001 .
bx "
bx -
1&
#2820
b1 '
1(
0&
#2830
b1110 +
b0 .
b0 "
b0 -
1&
#2840
b10 '
0(
0&
#2850
b1 .
1&
#2860
b11 '
0&
#2870
b10 .
1&
#2880
b100 '
0&
#2890
b11 .
1&
#2900
b101 '
0&
#2910
b100 .
1&
#2920
b110 '
0&
#2930
b101 .
1&
#2940
b111 '
0&
#2950
b110 .
1&
#2960
b1000 '
0&
#2970
b111 .
1&
#2980
b1001 '
0&
#2990
1!
b1000 .
1&
#3000
b0 '
b1111 #
b1111 )
0&
#3010
0!
b1001 .
bx "
bx -
1&
#3020
b1 '
1(
0&
#3030
b1111 +
b0 .
b0 "
b0 -
1&
#3040
b10 '
0(
0&
#3050
b1 .
1&
#3060
b11 '
0&
#3070
b10 .
1&
#3080
b100 '
0&
#3090
b11 .
1&
#3100
b101 '
0&
#3110
b100 .
1&
#3120
b110 '
0&
#3130
b101 .
1&
#3140
b111 '
0&
#3150
b110 .
1&
#3160
b1000 '
0&
#3170
b111 .
1&
#3180
b1001 '
0&
#3190
1!
b1000 .
1&
#3200
b0 '
b10000 #
b10000 )
0&
#3210
0!
b1001 .
bx "
bx -
1&
#3220
b1 '
1(
0&
#3230
b10000 +
b0 .
b0 "
b0 -
1&
#3240
b10 '
0(
0&
#3250
b1 .
1&
#3260
b11 '
0&
#3270
b10 .
1&
#3280
b100 '
0&
#3290
b11 .
1&
#3300
b101 '
0&
#3310
b100 .
1&
#3320
b110 '
0&
#3330
b101 .
1&
#3340
b111 '
0&
#3350
b110 .
1&
#3360
b1000 '
0&
#3370
b111 .
1&
#3380
b1001 '
0&
#3390
1!
b1000 .
1&
#3400
b0 '
b10001 #
b10001 )
0&
#3410
0!
b1001 .
bx "
bx -
1&
#3420
b1 '
1(
0&
#3430
b10001 +
b0 .
b0 "
b0 -
1&
#3440
b10 '
0(
0&
#3450
b1 .
1&
#3460
b11 '
0&
#3470
b10 .
1&
#3480
b100 '
0&
#3490
b11 .
1&
#3500
b101 '
0&
#3510
b100 .
1&
#3520
b110 '
0&
#3530
b101 .
1&
#3540
b111 '
0&
#3550
b110 .
1&
#3560
b1000 '
0&
#3570
b111 .
1&
#3580
b1001 '
0&
#3590
1!
b1000 .
1&
#3600
b0 '
b10010 #
b10010 )
0&
#3610
0!
b1001 .
bx "
bx -
1&
#3620
b1 '
1(
0&
#3630
b10010 +
b0 .
b0 "
b0 -
1&
#3640
b10 '
0(
0&
#3650
b1 .
1&
#3660
b11 '
0&
#3670
b10 .
1&
#3680
b100 '
0&
#3690
b11 .
1&
#3700
b101 '
0&
#3710
b100 .
1&
#3720
b110 '
0&
#3730
b101 .
1&
#3740
b111 '
0&
#3750
b110 .
1&
#3760
b1000 '
0&
#3770
b111 .
1&
#3780
b1001 '
0&
#3790
1!
b1000 .
1&
#3800
b0 '
b10011 #
b10011 )
0&
#3810
0!
b1001 .
bx "
bx -
1&
#3820
b1 '
1(
0&
#3830
b10011 +
b0 .
b0 "
b0 -
1&
#3840
b10 '
0(
0&
#3850
b1 .
1&
#3860
b11 '
0&
#3870
b10 .
1&
#3880
b100 '
0&
#3890
b11 .
1&
#3900
b101 '
0&
#3910
b100 .
1&
#3920
b110 '
0&
#3930
b101 .
1&
#3940
b111 '
0&
#3950
b110 .
1&
#3960
b1000 '
0&
#3970
b111 .
1&
#3980
b1001 '
0&
#3990
1!
b1000 .
1&
#4000
b0 '
b10100 #
b10100 )
0&
#4010
0!
b1001 .
bx "
bx -
1&
#4020
b1 '
1(
0&
#4030
b10100 +
b0 .
b0 "
b0 -
1&
#4040
b10 '
0(
0&
#4050
b1 .
1&
#4060
b11 '
0&
#4070
b10 .
1&
#4080
b100 '
0&
#4090
b11 .
1&
#4100
b101 '
0&
#4110
b100 .
1&
#4120
b110 '
0&
#4130
b101 .
1&
#4140
b111 '
0&
#4150
b110 .
1&
#4160
b1000 '
0&
#4170
b111 .
1&
#4180
b1001 '
0&
#4190
1!
b1000 .
1&
#4200
b0 '
b10101 #
b10101 )
0&
#4210
0!
b1001 .
bx "
bx -
1&
#4220
b1 '
1(
0&
#4230
b10101 +
b0 .
b0 "
b0 -
1&
#4240
b10 '
0(
0&
#4250
b1 .
1&
#4260
b11 '
0&
#4270
b10 .
1&
#4280
b100 '
0&
#4290
b11 .
1&
#4300
b101 '
0&
#4310
b100 .
1&
#4320
b110 '
0&
#4330
b101 .
1&
#4340
b111 '
0&
#4350
b110 .
1&
#4360
b1000 '
0&
#4370
b111 .
1&
#4380
b1001 '
0&
#4390
1!
b1000 .
1&
#4400
b0 '
b10110 #
b10110 )
0&
#4410
0!
b1001 .
bx "
bx -
1&
#4420
b1 '
1(
0&
#4430
b10110 +
b0 .
b0 "
b0 -
1&
#4440
b10 '
0(
0&
#4450
b1 .
1&
#4460
b11 '
0&
#4470
b10 .
1&
#4480
b100 '
0&
#4490
b11 .
1&
#4500
b101 '
0&
#4510
b100 .
1&
#4520
b110 '
0&
#4530
b101 .
1&
#4540
b111 '
0&
#4550
b110 .
1&
#4560
b1000 '
0&
#4570
b111 .
1&
#4580
b1001 '
0&
#4590
1!
b1000 .
1&
#4600
b0 '
b10111 #
b10111 )
0&
#4610
0!
b1001 .
bx "
bx -
1&
#4620
b1 '
1(
0&
#4630
b10111 +
b0 .
b0 "
b0 -
1&
#4640
b10 '
0(
0&
#4650
b1 .
1&
#4660
b11 '
0&
#4670
b10 .
1&
#4680
b100 '
0&
#4690
b11 .
1&
#4700
b101 '
0&
#4710
b100 .
1&
#4720
b110 '
0&
#4730
b101 .
1&
#4740
b111 '
0&
#4750
b110 .
1&
#4760
b1000 '
0&
#4770
b111 .
1&
#4780
b1001 '
0&
#4790
1!
b1000 .
1&
#4800
b0 '
b11000 #
b11000 )
0&
#4810
0!
b1001 .
bx "
bx -
1&
#4820
b1 '
1(
0&
#4830
b11000 +
b0 .
b0 "
b0 -
1&
#4840
b10 '
0(
0&
#4850
b1 .
1&
#4860
b11 '
0&
#4870
b10 .
1&
#4880
b100 '
0&
#4890
b11 .
1&
#4900
b101 '
0&
#4910
b100 .
1&
#4920
b110 '
0&
#4930
b101 .
1&
#4940
b111 '
0&
#4950
b110 .
1&
#4960
b1000 '
0&
#4970
b111 .
1&
#4980
b1001 '
0&
#4990
1!
b1000 .
1&
#5000
b0 '
b11001 #
b11001 )
0&
#5010
0!
b1001 .
bx "
bx -
1&
#5020
b1 '
1(
0&
#5030
b11001 +
b0 .
b0 "
b0 -
1&
#5040
b10 '
0(
0&
#5050
b1 .
1&
#5060
b11 '
0&
#5070
b10 .
1&
#5080
b100 '
0&
#5090
b11 .
1&
#5100
b101 '
0&
#5110
b100 .
1&
#5120
b110 '
0&
#5130
b101 .
1&
#5140
b111 '
0&
#5150
b110 .
1&
#5160
b1000 '
0&
#5170
b111 .
1&
#5180
b1001 '
0&
#5190
1!
b1000 .
1&
#5200
b0 '
b11010 #
b11010 )
0&
#5210
0!
b1001 .
bx "
bx -
1&
#5220
b1 '
1(
0&
#5230
b11010 +
b0 .
b0 "
b0 -
1&
#5240
b10 '
0(
0&
#5250
b1 .
1&
#5260
b11 '
0&
#5270
b10 .
1&
#5280
b100 '
0&
#5290
b11 .
1&
#5300
b101 '
0&
#5310
b100 .
1&
#5320
b110 '
0&
#5330
b101 .
1&
#5340
b111 '
0&
#5350
b110 .
1&
#5360
b1000 '
0&
#5370
b111 .
1&
#5380
b1001 '
0&
#5390
1!
b1000 .
1&
#5400
b0 '
b11011 #
b11011 )
0&
#5410
0!
b1001 .
bx "
bx -
1&
#5420
b1 '
1(
0&
#5430
b11011 +
b0 .
b0 "
b0 -
1&
#5440
b10 '
0(
0&
#5450
b1 .
1&
#5460
b11 '
0&
#5470
b10 .
1&
#5480
b100 '
0&
#5490
b11 .
1&
#5500
b101 '
0&
#5510
b100 .
1&
#5520
b110 '
0&
#5530
b101 .
1&
#5540
b111 '
0&
#5550
b110 .
1&
#5560
b1000 '
0&
#5570
b111 .
1&
#5580
b1001 '
0&
#5590
1!
b1000 .
1&
#5600
b0 '
b11100 #
b11100 )
0&
#5610
0!
b1001 .
bx "
bx -
1&
#5620
b1 '
1(
0&
#5630
b11100 +
b0 .
b0 "
b0 -
1&
#5640
b10 '
0(
0&
#5650
b1 .
1&
#5660
b11 '
0&
#5670
b10 .
1&
#5680
b100 '
0&
#5690
b11 .
1&
#5700
b101 '
0&
#5710
b100 .
1&
#5720
b110 '
0&
#5730
b101 .
1&
#5740
b111 '
0&
#5750
b110 .
1&
#5760
b1000 '
0&
#5770
b111 .
1&
#5780
b1001 '
0&
#5790
1!
b1000 .
1&
#5800
b0 '
b11101 #
b11101 )
0&
#5810
0!
b1001 .
bx "
bx -
1&
#5820
b1 '
1(
0&
#5830
b11101 +
b0 .
b0 "
b0 -
1&
#5840
b10 '
0(
0&
#5850
b1 .
1&
#5860
b11 '
0&
#5870
b10 .
1&
#5880
b100 '
0&
#5890
b11 .
1&
#5900
b101 '
0&
#5910
b100 .
1&
#5920
b110 '
0&
#5930
b101 .
1&
#5940
b111 '
0&
#5950
b110 .
1&
#5960
b1000 '
0&
#5970
b111 .
1&
#5980
b1001 '
0&
#5990
1!
b1000 .
1&
#6000
b0 '
b11110 #
b11110 )
0&
#6010
0!
b1001 .
bx "
bx -
1&
#6020
b1 '
1(
0&
#6030
b11110 +
b0 .
b0 "
b0 -
1&
#6040
b10 '
0(
0&
#6050
b1 .
1&
#6060
b11 '
0&
#6070
b10 .
1&
#6080
b100 '
0&
#6090
b11 .
1&
#6100
b101 '
0&
#6110
b100 .
1&
#6120
b110 '
0&
#6130
b101 .
1&
#6140
b111 '
0&
#6150
b110 .
1&
#6160
b1000 '
0&
#6170
b111 .
1&
#6180
b1001 '
0&
#6190
1!
b1000 .
1&
#6200
b0 '
b11111 #
b11111 )
0&
#6210
0!
b1001 .
bx "
bx -
1&
#6220
b1 '
1(
0&
#6230
b11111 +
b0 .
b0 "
b0 -
1&
#6240
b10 '
0(
0&
#6250
b1 .
1&
#6260
b11 '
0&
#6270
b10 .
1&
#6280
b100 '
0&
#6290
b11 .
1&
#6300
b101 '
0&
#6310
b100 .
1&
#6320
b110 '
0&
#6330
b101 .
1&
#6340
b111 '
0&
#6350
b110 .
1&
#6360
b1000 '
0&
#6370
b111 .
1&
#6380
b1001 '
0&
#6390
1!
b1000 .
1&
#6400
b0 '
b100000 #
b100000 )
0&
#6410
0!
b1001 .
bx "
bx -
1&
#6420
b1 '
1(
0&
#6430
b100000 +
b0 .
b0 "
b0 -
1&
#6440
b10 '
0(
0&
#6450
b1 .
1&
#6460
b11 '
0&
#6470
b10 .
1&
#6480
b100 '
0&
#6490
b11 .
1&
#6500
b101 '
0&
#6510
b100 .
1&
#6520
b110 '
0&
#6530
b101 .
1&
#6540
b111 '
0&
#6550
b110 .
1&
#6560
b1000 '
0&
#6570
b111 .
1&
#6580
b1001 '
0&
#6590
1!
b1000 .
1&
#6600
b0 '
b100001 #
b100001 )
0&
#6610
0!
b1001 .
bx "
bx -
1&
#6620
b1 '
1(
0&
#6630
b100001 +
b0 .
b0 "
b0 -
1&
#6640
b10 '
0(
0&
#6650
b1 .
1&
#6660
b11 '
0&
#6670
b10 .
1&
#6680
b100 '
0&
#6690
b11 .
1&
#6700
b101 '
0&
#6710
b100 .
1&
#6720
b110 '
0&
#6730
b101 .
1&
#6740
b111 '
0&
#6750
b110 .
1&
#6760
b1000 '
0&
#6770
b111 .
1&
#6780
b1001 '
0&
#6790
1!
b1000 .
1&
#6800
b0 '
b100010 #
b100010 )
0&
#6810
0!
b1001 .
bx "
bx -
1&
#6820
b1 '
1(
0&
#6830
b100010 +
b0 .
b0 "
b0 -
1&
#6840
b10 '
0(
0&
#6850
b1 .
1&
#6860
b11 '
0&
#6870
b10 .
1&
#6880
b100 '
0&
#6890
b11 .
1&
#6900
b101 '
0&
#6910
b100 .
1&
#6920
b110 '
0&
#6930
b101 .
1&
#6940
b111 '
0&
#6950
b110 .
1&
#6960
b1000 '
0&
#6970
b111 .
1&
#6980
b1001 '
0&
#6990
1!
b1000 .
1&
#7000
b0 '
b100011 #
b100011 )
0&
#7010
0!
b1001 .
bx "
bx -
1&
#7020
b1 '
1(
0&
#7030
b100011 +
b0 .
b0 "
b0 -
1&
#7040
b10 '
0(
0&
#7050
b1 .
1&
#7060
b11 '
0&
#7070
b10 .
1&
#7080
b100 '
0&
#7090
b11 .
1&
#7100
b101 '
0&
#7110
b100 .
1&
#7120
b110 '
0&
#7130
b101 .
1&
#7140
b111 '
0&
#7150
b110 .
1&
#7160
b1000 '
0&
#7170
b111 .
1&
#7180
b1001 '
0&
#7190
1!
b1000 .
1&
#7200
b0 '
b100100 #
b100100 )
0&
#7210
0!
b1001 .
bx "
bx -
1&
#7220
b1 '
1(
0&
#7230
b100100 +
b0 .
b0 "
b0 -
1&
#7240
b10 '
0(
0&
#7250
b1 .
1&
#7260
b11 '
0&
#7270
b10 .
1&
#7280
b100 '
0&
#7290
b11 .
1&
#7300
b101 '
0&
#7310
b100 .
1&
#7320
b110 '
0&
#7330
b101 .
1&
#7340
b111 '
0&
#7350
b110 .
1&
#7360
b1000 '
0&
#7370
b111 .
1&
#7380
b1001 '
0&
#7390
1!
b1000 .
1&
#7400
b0 '
b100101 #
b100101 )
0&
#7410
0!
b1001 .
bx "
bx -
1&
#7420
b1 '
1(
0&
#7430
b100101 +
b0 .
b0 "
b0 -
1&
#7440
b10 '
0(
0&
#7450
b1 .
1&
#7460
b11 '
0&
#7470
b10 .
1&
#7480
b100 '
0&
#7490
b11 .
1&
#7500
b101 '
0&
#7510
b100 .
1&
#7520
b110 '
0&
#7530
b101 .
1&
#7540
b111 '
0&
#7550
b110 .
1&
#7560
b1000 '
0&
#7570
b111 .
1&
#7580
b1001 '
0&
#7590
1!
b1000 .
1&
#7600
b0 '
b100110 #
b100110 )
0&
#7610
0!
b1001 .
bx "
bx -
1&
#7620
b1 '
1(
0&
#7630
b100110 +
b0 .
b0 "
b0 -
1&
#7640
b10 '
0(
0&
#7650
b1 .
1&
#7660
b11 '
0&
#7670
b10 .
1&
#7680
b100 '
0&
#7690
b11 .
1&
#7700
b101 '
0&
#7710
b100 .
1&
#7720
b110 '
0&
#7730
b101 .
1&
#7740
b111 '
0&
#7750
b110 .
1&
#7760
b1000 '
0&
#7770
b111 .
1&
#7780
b1001 '
0&
#7790
1!
b1000 .
1&
#7800
b0 '
b100111 #
b100111 )
0&
#7810
0!
b1001 .
bx "
bx -
1&
#7820
b1 '
1(
0&
#7830
b100111 +
b0 .
b0 "
b0 -
1&
#7840
b10 '
0(
0&
#7850
b1 .
1&
#7860
b11 '
0&
#7870
b10 .
1&
#7880
b100 '
0&
#7890
b11 .
1&
#7900
b101 '
0&
#7910
b100 .
1&
#7920
b110 '
0&
#7930
b101 .
1&
#7940
b111 '
0&
#7950
b110 .
1&
#7960
b1000 '
0&
#7970
b111 .
1&
#7980
b1001 '
0&
#7990
1!
b1000 .
1&
#8000
b0 '
b101000 #
b101000 )
0&
#8010
0!
b1001 .
bx "
bx -
1&
#8020
b1 '
1(
0&
#8030
b101000 +
b0 .
b0 "
b0 -
1&
#8040
b10 '
0(
0&
#8050
b1 .
1&
#8060
b11 '
0&
#8070
b10 .
1&
#8080
b100 '
0&
#8090
b11 .
1&
#8100
b101 '
0&
#8110
b100 .
1&
#8120
b110 '
0&
#8130
b101 .
1&
#8140
b111 '
0&
#8150
b110 .
1&
#8160
b1000 '
0&
#8170
b111 .
1&
#8180
b1001 '
0&
#8190
1!
b1000 .
1&
#8200
b0 '
b101001 #
b101001 )
0&
#8210
0!
b1001 .
bx "
bx -
1&
#8220
b1 '
1(
0&
#8230
b101001 +
b0 .
b0 "
b0 -
1&
#8240
b10 '
0(
0&
#8250
b1 .
1&
#8260
b11 '
0&
#8270
b10 .
1&
#8280
b100 '
0&
#8290
b11 .
1&
#8300
b101 '
0&
#8310
b100 .
1&
#8320
b110 '
0&
#8330
b101 .
1&
#8340
b111 '
0&
#8350
b110 .
1&
#8360
b1000 '
0&
#8370
b111 .
1&
#8380
b1001 '
0&
#8390
1!
b1000 .
1&
#8400
b0 '
b101010 #
b101010 )
0&
#8410
0!
b1001 .
bx "
bx -
1&
#8420
b1 '
1(
0&
#8430
b101010 +
b0 .
b0 "
b0 -
1&
#8440
b10 '
0(
0&
#8450
b1 .
1&
#8460
b11 '
0&
#8470
b10 .
1&
#8480
b100 '
0&
#8490
b11 .
1&
#8500
b101 '
0&
#8510
b100 .
1&
#8520
b110 '
0&
#8530
b101 .
1&
#8540
b111 '
0&
#8550
b110 .
1&
#8560
b1000 '
0&
#8570
b111 .
1&
#8580
b1001 '
0&
#8590
1!
b1000 .
1&
#8600
b0 '
b101011 #
b101011 )
0&
#8610
0!
b1001 .
bx "
bx -
1&
#8620
b1 '
1(
0&
#8630
b101011 +
b0 .
b0 "
b0 -
1&
#8640
b10 '
0(
0&
#8650
b1 .
1&
#8660
b11 '
0&
#8670
b10 .
1&
#8680
b100 '
0&
#8690
b11 .
1&
#8700
b101 '
0&
#8710
b100 .
1&
#8720
b110 '
0&
#8730
b101 .
1&
#8740
b111 '
0&
#8750
b110 .
1&
#8760
b1000 '
0&
#8770
b111 .
1&
#8780
b1001 '
0&
#8790
1!
b1000 .
1&
#8800
b0 '
b101100 #
b101100 )
0&
#8810
0!
b1001 .
bx "
bx -
1&
#8820
b1 '
1(
0&
#8830
b101100 +
b0 .
b0 "
b0 -
1&
#8840
b10 '
0(
0&
#8850
b1 .
1&
#8860
b11 '
0&
#8870
b10 .
1&
#8880
b100 '
0&
#8890
b11 .
1&
#8900
b101 '
0&
#8910
b100 .
1&
#8920
b110 '
0&
#8930
b101 .
1&
#8940
b111 '
0&
#8950
b110 .
1&
#8960
b1000 '
0&
#8970
b111 .
1&
#8980
b1001 '
0&
#8990
1!
b1000 .
1&
#9000
b0 '
b101101 #
b101101 )
0&
#9010
0!
b1001 .
bx "
bx -
1&
#9020
b1 '
1(
0&
#9030
b101101 +
b0 .
b0 "
b0 -
1&
#9040
b10 '
0(
0&
#9050
b1 .
1&
#9060
b11 '
0&
#9070
b10 .
1&
#9080
b100 '
0&
#9090
b11 .
1&
#9100
b101 '
0&
#9110
b100 .
1&
#9120
b110 '
0&
#9130
b101 .
1&
#9140
b111 '
0&
#9150
b110 .
1&
#9160
b1000 '
0&
#9170
b111 .
1&
#9180
b1001 '
0&
#9190
1!
b1000 .
1&
#9200
b0 '
b101110 #
b101110 )
0&
#9210
0!
b1001 .
bx "
bx -
1&
#9220
b1 '
1(
0&
#9230
b101110 +
b0 .
b0 "
b0 -
1&
#9240
b10 '
0(
0&
#9250
b1 .
1&
#9260
b11 '
0&
#9270
b10 .
1&
#9280
b100 '
0&
#9290
b11 .
1&
#9300
b101 '
0&
#9310
b100 .
1&
#9320
b110 '
0&
#9330
b101 .
1&
#9340
b111 '
0&
#9350
b110 .
1&
#9360
b1000 '
0&
#9370
b111 .
1&
#9380
b1001 '
0&
#9390
1!
b1000 .
1&
#9400
b0 '
b101111 #
b101111 )
0&
#9410
0!
b1001 .
bx "
bx -
1&
#9420
b1 '
1(
0&
#9430
b101111 +
b0 .
b0 "
b0 -
1&
#9440
b10 '
0(
0&
#9450
b1 .
1&
#9460
b11 '
0&
#9470
b10 .
1&
#9480
b100 '
0&
#9490
b11 .
1&
#9500
b101 '
0&
#9510
b100 .
1&
#9520
b110 '
0&
#9530
b101 .
1&
#9540
b111 '
0&
#9550
b110 .
1&
#9560
b1000 '
0&
#9570
b111 .
1&
#9580
b1001 '
0&
#9590
1!
b1000 .
1&
